{"updated_at":"2026-07-16T21:18:14.881Z","count":186,"leads":[{"id":"gh_544592629","name":"ballerine-io/ballerine","source":"GitHub","vertical":"identity","term":"kyc","w":5,"ms":1784210178000,"eng":2406,"url":"https://github.com/ballerine-io/ballerine","desc":"Open-source infrastructure and data orchestration platform for risk decisioning","author":"ballerine-io","company":"Ballerine","website":"https://ballerine.com","score":100,"first_seen":1784236521706,"last_seen":1784236521706},{"id":"gh_1249322957","name":"SantanderAI/gen-fraud-graph","source":"GitHub","vertical":"identity","term":"aml","w":5,"ms":1784205792000,"eng":269,"url":"https://github.com/SantanderAI/gen-fraud-graph","desc":"Synthetic fraud graph generator for benchmarking graph-based fraud detection models in financial services.","author":"SantanderAI","company":"Santander AI Open Source","website":"https://www.santander.com/en/stories/santander-publishes-ai-projects-under-an-open-source-licence-to-ramp-up-shared-innovation","score":100,"first_seen":1784236521706,"last_seen":1784236521706},{"id":"gh_701058624","name":"walt-id/waltid-identity","source":"GitHub","vertical":"credential","term":"verifiable-credentials","w":5,"ms":1784235795000,"eng":295,"url":"https://github.com/walt-id/waltid-identity","desc":"All-in-one open-source identity and wallet toolkit.","author":"walt-id","company":"walt.id","website":"https://walt.id","score":100,"first_seen":1784236521706,"last_seen":1784236521706},{"id":"gh_221235091","name":"decentralized-identity/veramo","source":"GitHub","vertical":"credential","term":"ssi","w":5,"ms":1784222000000,"eng":543,"url":"https://github.com/decentralized-identity/veramo","desc":"A JavaScript Framework for Verifiable Data","author":"decentralized-identity","company":"Decentralized Identity Foundation","website":"https://identity.foundation","score":100,"first_seen":1784236521706,"last_seen":1784236521706},{"id":"code_expensify","name":"Expensify/App","source":"Building with","vertical":"identity","term":"uses Onfido","w":6,"ms":1784236395000,"eng":4943,"url":"https://github.com/Expensify/App","desc":"Ships the Onfido SDK in production code (Expensify/App)","company":"Expensify, Inc","website":"https://use.expensify.com","author":"expensify","vendor":"Onfido","score":100,"first_seen":1784236521706,"last_seen":1784236521706},{"id":"code_superteamdao","name":"SuperteamDAO/earn","source":"Building with","vertical":"identity","term":"uses Sumsub","w":6,"ms":1784032134000,"eng":245,"url":"https://github.com/SuperteamDAO/earn","desc":"Ships the Sumsub SDK in production code (SuperteamDAO/earn)","company":"Superteam Labs","website":"https://superteam.fun/","author":"superteamdao","vendor":"Sumsub","score":100,"first_seen":1784236521706,"last_seen":1784236521706},{"id":"gh_238708260","name":"iotaledger/identity","source":"GitHub","vertical":"credential","term":"verifiable-credentials","w":5,"ms":1784196393000,"eng":350,"url":"https://github.com/iotaledger/identity","desc":"Implementation of the Decentralized Identity standards such as DID and Verifiable Credentials by W3C for the IOTA MoveVM. ","author":"iotaledger","company":"IOTA","website":"https://iota.org","score":99,"first_seen":1784236521706,"last_seen":1784236521706},{"id":"gh_127560664","name":"decentralized-identity/ethr-did-resolver","source":"GitHub","vertical":"credential","term":"ssi","w":5,"ms":1784167056000,"eng":233,"url":"https://github.com/decentralized-identity/ethr-did-resolver","desc":"DID resolver for Ethereum Addresses with support for key management","author":"decentralized-identity","company":"Decentralized Identity Foundation","website":"https://identity.foundation","score":99,"first_seen":1784236521706,"last_seen":1784236521706},{"id":"code_common-ground-dao","name":"Common-Ground-DAO/commonground","source":"Building with","vertical":"identity","term":"uses Sumsub","w":6,"ms":1784235957000,"eng":53,"url":"https://github.com/Common-Ground-DAO/commonground","desc":"Ships the Sumsub SDK in production code (Common-Ground-DAO/commonground)","company":"Common Ground","website":"https://commonground.cg","author":"common-ground-dao","vendor":"Sumsub","score":98,"first_seen":1784236521706,"last_seen":1784236521706},{"id":"code_geyserfund","name":"geyserfund/geyser-app","source":"Building with","vertical":"identity","term":"uses Sumsub","w":6,"ms":1784209936000,"eng":61,"url":"https://github.com/geyserfund/geyser-app","desc":"Ships the Sumsub SDK in production code (geyserfund/geyser-app)","company":"geyser","website":"https://geyser.fund/","author":"geyserfund","vendor":"Sumsub","score":98,"first_seen":1784236521706,"last_seen":1784236521706},{"id":"code_drips-network","name":"drips-network/app","source":"Building with","vertical":"identity","term":"uses Sumsub","w":6,"ms":1784203394000,"eng":52,"url":"https://github.com/drips-network/app","desc":"Ships the Sumsub SDK in production code (drips-network/app)","company":"Drips","website":"https://drips.network/","author":"drips-network","vendor":"Sumsub","score":97,"first_seen":1784236521706,"last_seen":1784236521706},{"id":"gh_631660186","name":"w3c-fedid/digital-credentials","source":"GitHub","vertical":"credential","term":"verifiable-credentials","w":5,"ms":1784190745000,"eng":162,"url":"https://github.com/w3c-fedid/digital-credentials","desc":"Digital Credentials API","author":"w3c-fedid","company":"W3C FedID WG","website":"https://www.w3.org/groups/wg/fedid/","score":96,"first_seen":1784236521706,"last_seen":1784236521706},{"id":"gh_588557077","name":"impierce/identity-wallet","source":"GitHub","vertical":"credential","term":"verifiable-credentials","w":5,"ms":1784229626000,"eng":131,"url":"https://github.com/impierce/identity-wallet","desc":"A Tauri-based Identity Wallet for people to manage Decentralized Identities and Verifiable Credentials.","author":"impierce","company":"Impierce Technologies","website":"www.impierce.com","score":95,"first_seen":1784236521706,"last_seen":1784236521706},{"id":"code_diaspora-connect-global","name":"Diaspora-Connect-Global/diasporaconnect","source":"Building with","vertical":"identity","term":"uses Onfido","w":6,"ms":1784207441000,"eng":0,"url":"https://github.com/Diaspora-Connect-Global/diasporaconnect","desc":"Ships the Onfido SDK in production code (Diaspora-Connect-Global/diasporaconnect)","company":"Diaspora Connect Global","website":"https://diasporaconnectglobal.com/","author":"diaspora-connect-global","vendor":"Onfido","score":94,"first_seen":1784236521706,"last_seen":1784236521706},{"id":"code_masumi-network","name":"masumi-network/masumi-saas","source":"Building with","vertical":"identity","term":"uses Sumsub","w":6,"ms":1784231604000,"eng":3,"url":"https://github.com/masumi-network/masumi-saas","desc":"Ships the Sumsub SDK in production code (masumi-network/masumi-saas)","company":"Masumi Network","website":"https://www.masumi.network/","author":"masumi-network","vendor":"Sumsub","score":94,"first_seen":1784236521706,"last_seen":1784236521706},{"id":"code_dfxswiss","name":"DFXswiss/services","source":"Building with","vertical":"identity","term":"uses Sumsub","w":6,"ms":1784215680000,"eng":10,"url":"https://github.com/DFXswiss/services","desc":"Ships the Sumsub SDK in production code (DFXswiss/services)","company":"DFX","website":"DFX.swiss","author":"dfxswiss","vendor":"Sumsub","score":94,"first_seen":1784236521706,"last_seen":1784236521706},{"id":"code_stellar-trust-escrow","name":"Stellar-Trust-Escrow/stellar-trust-escrow","source":"Building with","vertical":"identity","term":"uses Sumsub","w":6,"ms":1784203342000,"eng":5,"url":"https://github.com/Stellar-Trust-Escrow/stellar-trust-escrow","desc":"Ships the Sumsub SDK in production code (Stellar-Trust-Escrow/stellar-trust-escrow)","company":"stellar-trust-escrow","website":null,"author":"stellar-trust-escrow","vendor":"Sumsub","score":94,"first_seen":1784236521706,"last_seen":1784236521706},{"id":"gh_429950091","name":"bcgov/bc-wallet-mobile","source":"GitHub","vertical":"credential","term":"verifiable-credentials","w":5,"ms":1784235980000,"eng":83,"url":"https://github.com/bcgov/bc-wallet-mobile","desc":"BC Wallet to hold Verifiable Credentials","author":"bcgov","company":"bcgov","website":"https://github.com/bcgov/BC-Policy-Framework-For-GitHub","score":91,"first_seen":1784236521706,"last_seen":1784236521706},{"id":"code_entrustcorporation","name":"EntrustCorporation/idaas-auth-js","source":"Building with","vertical":"identity","term":"uses Onfido","w":6,"ms":1784064384000,"eng":1,"url":"https://github.com/EntrustCorporation/idaas-auth-js","desc":"Ships the Onfido SDK in production code (EntrustCorporation/idaas-auth-js)","company":"Entrust","website":"https://www.entrust.com/","author":"entrustcorporation","vendor":"Onfido","score":91,"first_seen":1784236521706,"last_seen":1784236521706},{"id":"gh_486055750","name":"learningeconomy/LearnCard","source":"GitHub","vertical":"credential","term":"verifiable-credentials","w":5,"ms":1784235247000,"eng":67,"url":"https://github.com/learningeconomy/LearnCard","desc":"✨ Open-source lifelong learning passport that empowers learners to collect, own, and share their skills and experiences. 💖","author":"learningeconomy","company":"Learning Economy","website":"www.learningeconomy.io","score":90,"first_seen":1784236521706,"last_seen":1784236521706},{"id":"gh_512835706","name":"hyperledger-identus/cloud-agent","source":"GitHub","vertical":"credential","term":"ssi","w":5,"ms":1783948356000,"eng":94,"url":"https://github.com/hyperledger-identus/cloud-agent","desc":"Identus Cloud Agent","author":"hyperledger-identus","company":"Hyperledger Identus","website":"https://www.lfdecentralizedtrust.org/","score":88,"first_seen":1784236521706,"last_seen":1784236521706},{"id":"gh_1080174450","name":"trustknots/vcknots","source":"GitHub","vertical":"credential","term":"verifiable-credentials","w":5,"ms":1784225626000,"eng":33,"url":"https://github.com/trustknots/vcknots","desc":"Pluggable framework for building Verifiable Credentials ecosystems","author":"trustknots","company":"Trust Knots","website":null,"score":87,"first_seen":1784236521706,"last_seen":1784236521706},{"id":"gh_372712530","name":"Lumoin/Verifiable","source":"GitHub","vertical":"credential","term":"ssi","w":5,"ms":1784178147000,"eng":39,"url":"https://github.com/Lumoin/Verifiable","desc":"A .NET implementation of decentralized identifiers and verifiable credentials, some associated protocols and cryptographic routines.","author":"Lumoin","company":"Lumoin","website":"https://lumoin.com","score":87,"first_seen":1784236521706,"last_seen":1784236521706},{"id":"gh_1238000894","name":"proof/proof-vc-common","source":"GitHub","vertical":"credential","term":"verifiable-credentials","w":5,"ms":1784209498000,"eng":23,"url":"https://github.com/proof/proof-vc-common","desc":"A digital passport. Verified once, usable everywhere.","author":"proof","company":"Proof","website":"https://proof.com","score":86,"first_seen":1784236521706,"last_seen":1784236521706},{"id":"gh_1258562044","name":"proof/proof-vc-web","source":"GitHub","vertical":"credential","term":"verifiable-credentials","w":5,"ms":1784192640000,"eng":19,"url":"https://github.com/proof/proof-vc-web","desc":"Web Components for Proof Digital Credentials.","author":"proof","company":"Proof","website":"https://proof.com","score":86,"first_seen":1784236521706,"last_seen":1784236521706},{"id":"gh_731107747","name":"ForkbombEu/credimi","source":"GitHub","vertical":"credential","term":"ssi","w":5,"ms":1784225926000,"eng":16,"url":"https://github.com/ForkbombEu/credimi","desc":"Automated interoperability/conformance testing and hub for EUDI and SSI.","author":"ForkbombEu","company":"Forkbomb","website":"https://forkbomb.solutions","score":86,"first_seen":1784236521706,"last_seen":1784236521706},{"id":"gh_862200853","name":"procivis/one-core","source":"GitHub","vertical":"credential","term":"ssi","w":5,"ms":1783500987000,"eng":160,"url":"https://github.com/procivis/one-core","desc":"Issue, hold and verify digital identities and credentials on any device with eIDAS 2.0 compliancy, ISO 18013-5 mdocs, IETF SD-JWT VC, OID4VC, and W3C VCs.","author":"procivis","company":"Procivis","website":"https://procivis.ch","score":86,"first_seen":1784236521706,"last_seen":1784236521706},{"id":"gh_1141709828","name":"tyleroneshs/risk-fraud-financial-analytics-portfolio","source":"GitHub","vertical":"identity","term":"KYC / identity","w":5,"ms":1784235362000,"eng":0,"url":"https://github.com/tyleroneshs/risk-fraud-financial-analytics-portfolio","desc":"🔍 Analyze transaction data to identify fraud risks, streamline alert reviews, and ensure compliance in AML and KYC contexts using Excel-driven techniques.","author":"tyleroneshs","website":null,"score":85,"first_seen":1784236521706,"last_seen":1784236521706},{"id":"gh_656155669","name":"khma-92/Veriflow","source":"GitHub","vertical":"identity","term":"kyc","w":5,"ms":1784233744000,"eng":1,"url":"https://github.com/khma-92/Veriflow","desc":"🔍 Verify identities remotely with secure API features like live photo checks, document validation, and structured data extraction.","author":"khma-92","website":null,"score":85,"first_seen":1784236521706,"last_seen":1784236521706},{"id":"gh_1200817985","name":"sharonhopeless346/rwa-compliance-checklist","source":"GitHub","vertical":"identity","term":"KYC / identity","w":5,"ms":1784229821000,"eng":0,"url":"https://github.com/sharonhopeless346/rwa-compliance-checklist","desc":"Track RWA compliance with an open-source checklist for KYC, AML, onboarding, transfer rules, and multi-jurisdiction mapping","author":"sharonhopeless346","website":null,"score":85,"first_seen":1784236521706,"last_seen":1784236521706},{"id":"gh_212010832","name":"ZafarAabid/face-id","source":"GitHub","vertical":"identity","term":"kyc","w":5,"ms":1784229189000,"eng":2,"url":"https://github.com/ZafarAabid/face-id","desc":"Deliver real-time face detection and recognition in the browser using FastAPI, WebSockets, and GPU-accelerated InsightFace models.","author":"ZafarAabid","company":"ZafarAabidBL","website":null,"score":85,"first_seen":1784236521706,"last_seen":1784236521706},{"id":"gh_1282533046","name":"anil-turan/aml-fraud-detection","source":"GitHub","vertical":"identity","term":"AML / compliance","w":5,"ms":1784223764000,"eng":0,"url":"https://github.com/anil-turan/aml-fraud-detection","desc":"Multi-model fraud detection pipeline: Isolation Forest + LSTM Autoencoder + XGBoost ensemble (AUC-PR 0.93). Covers 5 AML typologies (structuring, velocity, geo-risk). Integrated SAR triage workflow aligned with POCA 2002 & FCA ML Regs 2017. 19 tests.","author":"anil-turan","company":"Anil Turan","website":null,"score":85,"first_seen":1784236521706,"last_seen":1784236521706},{"id":"gh_1230657261","name":"dovedownpat422/sanctioncheck","source":"GitHub","vertical":"identity","term":"KYC / identity","w":5,"ms":1784221740000,"eng":0,"url":"https://github.com/dovedownpat422/sanctioncheck","desc":"Screen entities against EU, UN, OFAC, and DGT sanctions lists using a fast, scriptable command-line tool for AML and KYC compliance workflows.","author":"dovedownpat422","website":null,"score":85,"first_seen":1784236521706,"last_seen":1784236521706},{"id":"gh_1290151562","name":"verifiedstack/verifiedstack-lite","source":"GitHub","vertical":"identity","term":"KYC / identity","w":5,"ms":1784217289000,"eng":0,"url":"https://github.com/verifiedstack/verifiedstack-lite","desc":"Free Next.js SaaS starter: auth, passkeys, 2FA, orgs with RBAC. Base of VerifiedStack, the KYC-ready kit.","author":"verifiedstack","company":"VerifiedStack","website":"https://www.verifiedstack.app","score":85,"first_seen":1784236521706,"last_seen":1784236521706},{"id":"gh_1238269192","name":"firefly-operationOS/flydocs","source":"GitHub","vertical":"identity","term":"kyc","w":5,"ms":1784205458000,"eng":0,"url":"https://github.com/firefly-operationOS/flydocs","desc":"Pure-multimodal IDP service — extract structured fields with bounding boxes from PDFs, images, Office docs and archives, then validate, authenticity-check, judge, and evaluate business rules. Sync + EDA async APIs on Python 3.13 over fireflyframework-pyfly and -agentic.","author":"firefly-operationOS","company":"Firefly OperationOS","website":"https://fireflysoftware.io","score":85,"first_seen":1784236521706,"last_seen":1784236521706},{"id":"gh_1037928327","name":"vouchsafe/vouchsafe-node","source":"GitHub","vertical":"identity","term":"KYC / identity","w":5,"ms":1784195105000,"eng":3,"url":"https://github.com/vouchsafe/vouchsafe-node","desc":"Official TypeScript and Node.js library for the Vouchsafe identity platform. Use it for easy KYC checks, identity verification, remote right-to-work and more.","author":"vouchsafe","company":"Vouchsafe","website":"vouchsafe.id","score":85,"first_seen":1784236521706,"last_seen":1784236521706},{"id":"gh_1045224578","name":"vouchsafe/vouchsafe-php","source":"GitHub","vertical":"identity","term":"KYC / identity","w":5,"ms":1784194941000,"eng":2,"url":"https://github.com/vouchsafe/vouchsafe-php","desc":"Official PHP library for the Vouchsafe identity platform. Use it for easy KYC checks, identity verification, remote right-to-work and more.","author":"vouchsafe","company":"Vouchsafe","website":"vouchsafe.id","score":85,"first_seen":1784236521706,"last_seen":1784236521706},{"id":"gh_1111164423","name":"Filidetan597/finomaly","source":"GitHub","vertical":"identity","term":"aml","w":5,"ms":1784233797000,"eng":2,"url":"https://github.com/Filidetan597/finomaly","desc":"📊 Detect anomalies in financial transactions with Finomaly, a modular, open-source Python library supporting both rule-based and machine learning methods.","author":"Filidetan597","website":null,"score":85,"first_seen":1784236521706,"last_seen":1784236521706},{"id":"gh_383360915","name":"Suraj0099/SOLANA-AML-Checker","source":"GitHub","vertical":"identity","term":"AML / compliance","w":5,"ms":1784232626000,"eng":1,"url":"https://github.com/Suraj0099/SOLANA-AML-Checker","desc":"🔍 Screen Solana wallets and NFTs for suspicious activity with this free AML checker tool, ensuring safer transactions on the blockchain.","author":"Suraj0099","website":null,"score":85,"first_seen":1784236521706,"last_seen":1784236521706},{"id":"gh_1265951850","name":"trex0092/HAWKEYE-STERLING-RA","source":"GitHub","vertical":"identity","term":"AML / compliance","w":5,"ms":1784236330000,"eng":1,"url":"https://github.com/trex0092/HAWKEYE-STERLING-RA","desc":"Hawkeye Sterling — AML/CFT Entity Risk Assessment for DPMS, with an AI compliance advisor and operations console (static Netlify app, no build step).","author":"trex0092","company":"trex0092","website":null,"score":85,"first_seen":1784236521706,"last_seen":1784236521706},{"id":"gh_1302583680","name":"M-Amine01/responsive-dynamic-qml-gui_single_file-","source":"GitHub","vertical":"identity","term":"aml","w":5,"ms":1784215619000,"eng":0,"url":"https://github.com/M-Amine01/responsive-dynamic-qml-gui_single_file-","desc":"Dynamic real-time GUI (Single File QML)","author":"M-Amine01","website":null,"score":85,"first_seen":1784236521706,"last_seen":1784236521706},{"id":"gh_1299713059","name":"karol-duda/sanctions-screening-validation","source":"GitHub","vertical":"identity","term":"aml","w":5,"ms":1784214667000,"eng":0,"url":"https://github.com/karol-duda/sanctions-screening-validation","desc":"Operational validation of the OpenSanctions screening stack: benchmark audit, capacity-calibrated thresholds, segment error analysis, and a 19M-record live-registry test (UK PSC + GLEIF vs EU sanctions list)","author":"karol-duda","company":"Karol Duda","website":"https://www.linkedin.com/in/karol-duda-022525238/","score":85,"first_seen":1784236521706,"last_seen":1784236521706},{"id":"gh_1281833127","name":"rrahimi-uci/rl-anti-money-laundry","source":"GitHub","vertical":"identity","term":"aml","w":5,"ms":1784213381000,"eng":1,"url":"https://github.com/rrahimi-uci/rl-anti-money-laundry","desc":"Reinforcement learning (PPO/A2C/DQN) that dynamically tunes Anti-Money-Laundering risk-scoring weights per case — Gymnasium env, FastAPI backend, and a React training dashboard.","author":"rrahimi-uci","company":"Reza Rahimi","website":"https://github.com/rrahimi-uci","score":85,"first_seen":1784236521706,"last_seen":1784236521706},{"id":"gh_1285980274","name":"leen449/GraphShield","source":"GitHub","vertical":"identity","term":"AML / compliance","w":5,"ms":1784206513000,"eng":0,"url":"https://github.com/leen449/GraphShield","desc":"GraphShield is an Explainable AI-powered AML detection using Graph Neural Networks, Machine Learning, and interactive fraud network visualization.","author":"leen449","company":"LEEN ABDURAHMAN SAUD BINMUEQAL","website":null,"score":85,"first_seen":1784236521706,"last_seen":1784236521706},{"id":"gh_1085848707","name":"Brandaogabriel29/AI-auth-toolkit","source":"GitHub","vertical":"identity","term":"identity-verification","w":5,"ms":1784233252000,"eng":0,"url":"https://github.com/Brandaogabriel29/AI-auth-toolkit","desc":"🤖 Streamline AI authentication processes with this toolkit, enhancing security and user experience for your applications.","author":"Brandaogabriel29","company":"Gabriel Brandão","website":null,"score":85,"first_seen":1784236521706,"last_seen":1784236521706},{"id":"gh_1243719300","name":"kompalwargangotri/video-kyc-aml-detection","source":"GitHub","vertical":"identity","term":"KYC / identity","w":5,"ms":1784222773000,"eng":0,"url":"https://github.com/kompalwargangotri/video-kyc-aml-detection","desc":"AI-powered Video KYC and AML verification prototype using YOLOv8, OCR, deepfake detection, anomaly detection, FastAPI and SQLite.","author":"kompalwargangotri","company":"Gangotri Kompalwar","website":"https://kompalwargangotri.github.io/","score":85,"first_seen":1784236521706,"last_seen":1784236521706},{"id":"gh_1281501205","name":"bcgov/vc-common-service","source":"GitHub","vertical":"credential","term":"credentials","w":5,"ms":1784233986000,"eng":0,"url":"https://github.com/bcgov/vc-common-service","desc":"A multi-tenant API and UI providing a format-agnostic abstraction layer for Verifiable Credential operations. It normalizes issue/verify/hold patterns across credential formats and back-end agents.","author":"bcgov","company":"bcgov","website":"https://github.com/bcgov/BC-Policy-Framework-For-GitHub","score":85,"first_seen":1784236521706,"last_seen":1784236521706},{"id":"gh_907674560","name":"student-arun/TrueState-Protocol","source":"GitHub","vertical":"credential","term":"verifiable-credentials","w":5,"ms":1784232414000,"eng":1,"url":"https://github.com/student-arun/TrueState-Protocol","desc":"🔒 Create unique, self-verifying digital artifacts with True State Protocol, featuring dual-mode architecture for flexible verification and ownership tracking.","author":"student-arun","website":null,"score":85,"first_seen":1784236521706,"last_seen":1784236521706},{"id":"gh_1279620226","name":"registrystack/registry-stack","source":"GitHub","vertical":"credential","term":"verifiable-credentials","w":5,"ms":1784232014000,"eng":1,"url":"https://github.com/registrystack/registry-stack","desc":"Build registry-facing services over data institutions already hold: protected read APIs, governed evidence, credentials, and audit.","author":"registrystack","website":null,"score":85,"first_seen":1784236521706,"last_seen":1784236521706},{"id":"gh_1116295901","name":"OlympusLedgerOrg/Olympus","source":"GitHub","vertical":"credential","term":"verifiable-credentials","w":5,"ms":1784207414000,"eng":2,"url":"https://github.com/OlympusLedgerOrg/Olympus","desc":"Olympus — a verifiable ledger for sensitive information. Tamper-evident Sparse Merkle Tree ledger with redaction proofs via a Folded Signed Merkle tree, soulbound credentials, and offline-verifiable court evidence. Rust + Tauri 2 desktop app, no servers required.","author":"OlympusLedgerOrg","company":"Anthony Smith","website":null,"score":85,"first_seen":1784236521706,"last_seen":1784236521706},{"id":"gh_1285988816","name":"b7n0de/proofbundle","source":"GitHub","vertical":"credential","term":"verifiable-credentials","w":5,"ms":1784234737000,"eng":1,"url":"https://github.com/b7n0de/proofbundle","desc":"Offline cryptographic receipts for AI evaluation results — Ed25519 + RFC 6962 Merkle + optional SD-JWT. Integrity, not truth","author":"b7n0de","company":"kraxo","website":null,"score":85,"first_seen":1784236521706,"last_seen":1784236521706},{"id":"gh_1155562256","name":"hiero-ledger/heka-identity-platform","source":"GitHub","vertical":"credential","term":"verifiable-credentials","w":5,"ms":1784160004000,"eng":15,"url":"https://github.com/hiero-ledger/heka-identity-platform","desc":"Decentralized identity platform for the Hiero ecosystem","author":"hiero-ledger","company":"Hiero Ledger","website":"https://hiero.org","score":85,"first_seen":1784236521706,"last_seen":1784236521706},{"id":"gh_1211876340","name":"eep-dev/EEP","source":"GitHub","vertical":"credential","term":"verifiable-credentials","w":5,"ms":1784143081000,"eng":22,"url":"https://github.com/eep-dev/EEP","desc":"An open standard for push-based, verifiable communication between digital entities and agents that follow them.","author":"eep-dev","company":"Entity Engagement Protocol (EEP)","website":"https://eep.dev","score":85,"first_seen":1784236521706,"last_seen":1784236521706},{"id":"gh_140664980","name":"xProgrammerAlvz/bank-mcp","source":"GitHub","vertical":"fintech","term":"banking app","w":5,"ms":1784236452000,"eng":0,"url":"https://github.com/xProgrammerAlvz/bank-mcp","desc":"Enable AI assistants to securely access and read bank account data for balances, transactions, and spending insights without manual downloads or spreadsheets.","author":"xProgrammerAlvz","website":null,"score":85,"first_seen":1784236521706,"last_seen":1784236521706},{"id":"gh_1130619240","name":"archetech/archon","source":"GitHub","vertical":"credential","term":"ssi","w":5,"ms":1784235552000,"eng":5,"url":"https://github.com/archetech/archon","desc":"Full stack decentralized identity platform and reference implementation for the did:cid DID method","author":"archetech","company":"Archetech","website":"http://www.archetech.com","score":85,"first_seen":1784236521706,"last_seen":1784236521706},{"id":"gh_1177773157","name":"trustoverip/dtgwg-trust-tasks-tf","source":"GitHub","vertical":"credential","term":"ssi","w":5,"ms":1784206735000,"eng":3,"url":"https://github.com/trustoverip/dtgwg-trust-tasks-tf","desc":"Trust Tasks - Transport Agnostic protocol for managing Tasks","author":"trustoverip","company":"Trust over IP","website":"https://trustoverip.org","score":85,"first_seen":1784236521706,"last_seen":1784236521706},{"id":"gh_1166085355","name":"OpenVTC/verifiable-trust-infrastructure","source":"GitHub","vertical":"credential","term":"ssi","w":5,"ms":1784199664000,"eng":6,"url":"https://github.com/OpenVTC/verifiable-trust-infrastructure","desc":"Verifiable Trust Infrastructure (VTI)","author":"OpenVTC","company":"OpenVTC","website":"https://www.lfdecentralizedtrust.org/","score":85,"first_seen":1784236521706,"last_seen":1784236521706},{"id":"gh_1176132614","name":"ma3u/MinimumViableHealthDataspacev2","source":"GitHub","vertical":"credential","term":"ssi","w":5,"ms":1784189711000,"eng":7,"url":"https://github.com/ma3u/MinimumViableHealthDataspacev2","desc":"The demo models a concrete EHDS secondary-use scenario: a clinical research organisation  wants to run a drug-repurposing study using synthetic patient data held by a hospital, with access governed by a Health Data Access Body. All five layers of this scenario live in a single Neo4j knowledge graph.","author":"ma3u","company":"Matthias Buchhorn","website":"https://www.linkedin.com/in/mbuchhorn","score":85,"first_seen":1784236521706,"last_seen":1784236521706},{"id":"gh_1075937331","name":"affinidi/affinidi-meetingplace-reference-app","source":"GitHub","vertical":"credential","term":"ssi","w":5,"ms":1784212436000,"eng":2,"url":"https://github.com/affinidi/affinidi-meetingplace-reference-app","desc":"Affinidi Meeting Place - open-source reference implementation of a chat application based on DIDComm v2.1 messaging protocol","author":"affinidi","company":"Affinidi","website":"www.affinidi.com","score":85,"first_seen":1784236521706,"last_seen":1784236521706},{"id":"gh_554110570","name":"european-epc-competence-center/vc-verifier","source":"GitHub","vertical":"credential","term":"ssi","w":5,"ms":1784197002000,"eng":10,"url":"https://github.com/european-epc-competence-center/vc-verifier","desc":"The EECC Verifier for Verifiable Credentials provides a verification API as well as the corresponding UI.","author":"european-epc-competence-center","company":" European EPC Competence Center GmbH (EECC)","website":"https://www.eecc.de","score":85,"first_seen":1784236521706,"last_seen":1784236521706},{"id":"gh_588124318","name":"hyperledger-identus/docs","source":"GitHub","vertical":"credential","term":"ssi","w":5,"ms":1784169780000,"eng":14,"url":"https://github.com/hyperledger-identus/docs","desc":"Documentation website for the Identus Platform","author":"hyperledger-identus","company":"Hyperledger Identus","website":"https://www.lfdecentralizedtrust.org/","score":85,"first_seen":1784236521706,"last_seen":1784236521706},{"id":"hire_gusto","name":"Gusto","source":"Hiring","company":"Gusto","vertical":"identity","term":"hiring: Compliance Manager, Broker-Dealer & Investment Adviser","w":4,"ms":1784219928000,"eng":120,"url":"https://job-boards.greenhouse.io/gusto/jobs/8024433","desc":"Open roles: Compliance Manager, Broker-Dealer & Investment Adviser · Financial Services Compliance Lead · Fraud Investigations Analyst · Legal & Compliance Tech IT Product Manager","author":"Gusto","score":85,"first_seen":1784236521706,"last_seen":1784236521706},{"id":"hire_nubank","name":"Nubank","source":"Hiring","company":"Nubank","vertical":"identity","term":"hiring: AML QA Analyst","w":4,"ms":1784229899000,"eng":120,"url":"https://job-boards.greenhouse.io/nubank/jobs/7976871","desc":"Open roles: AML QA Analyst · AML Senior Expert · AML Specialist  · Consumer Compliance and CRA Analyst","author":"Nubank","score":85,"first_seen":1784236521706,"last_seen":1784236521706},{"id":"hire_tide","name":"Tide","source":"Hiring","company":"Tide","vertical":"identity","term":"hiring: Information Security Compliance Manager (India)","w":4,"ms":1784233694000,"eng":120,"url":"https://job-boards.greenhouse.io/tide/jobs/7731764003","desc":"Open roles: Information Security Compliance Manager (India) · Lead, Onboarding, KYC, UK · Regulatory Risk & Compliance Lead (Fixed-Term Contract) · Regulatory Risk & Compliance Specialist - UK","author":"Tide","score":85,"first_seen":1784236521706,"last_seen":1784236521706},{"id":"gh_1302461720","name":"lau-sam/identite-ts","source":"GitHub","vertical":"identity","term":"kyc","w":5,"ms":1784187852000,"eng":1,"url":"https://github.com/lau-sam/identite-ts","desc":"Extraction 100% client-side de documents d'identité français (CNI, passeport, carte Vitale) | French ID documents to typed JSON via MRZ, NIR & 2D-DOC parsing. No server, GDPR-friendly.","author":"lau-sam","company":"LaPoule","website":null,"score":84,"first_seen":1784236521706,"last_seen":1784236521706},{"id":"gh_1302644036","name":"walawala254/payouts-transaction-monitoring-engine-mvp","source":"GitHub","vertical":"identity","term":"aml","w":5,"ms":1784199273000,"eng":0,"url":"https://github.com/walawala254/payouts-transaction-monitoring-engine-mvp","desc":"Payouts Transaction Monitoring Engine MVP — a governed Streamlit monitoring and investigation workbench for synthetic demonstrations.","author":"walawala254","company":" Bryson D","website":null,"score":84,"first_seen":1784236521706,"last_seen":1784236521706},{"id":"gh_1287093175","name":"netlinklabs/netlink-bio","source":"GitHub","vertical":"credential","term":"credentials","w":5,"ms":1784203953000,"eng":0,"url":"https://github.com/netlinklabs/netlink-bio","desc":"Digital identity platform with bio links, landing pages, and crypto payments.","author":"netlinklabs","company":"Netlink Labs","website":"https://netlinktoken.com","score":84,"first_seen":1784236521706,"last_seen":1784236521706},{"id":"gh_841620378","name":"trinsic-id/sdk","source":"GitHub","vertical":"identity","term":"identity-verification","w":5,"ms":1784140337000,"eng":8,"url":"https://github.com/trinsic-id/sdk","desc":"This repository contains the samples for all major languages and frameworks. It also contains our UI SDKs to launch verification flows using the Trinsic widget. ","author":"trinsic-id","company":"Trinsic","website":"https://trinsic.id","score":84,"first_seen":1784236521706,"last_seen":1784236521706},{"id":"gh_1160867653","name":"in2workspace/eudistack-core-verifier","source":"GitHub","vertical":"credential","term":"verifiable-credentials","w":5,"ms":1784197495000,"eng":0,"url":"https://github.com/in2workspace/eudistack-core-verifier","desc":"OID4VP/DCQL Verifier for the EUDIStack platform — eIDAS 2.0 compliant credential verification service built with Java 25 and Spring WebFlux","author":"in2workspace","company":"ALTIA CONSULTORES, SA","website":"https://intranet.altia.es/","score":84,"first_seen":1784236521706,"last_seen":1784236521706},{"id":"gh_1302636131","name":"gennarodambrosio-hub/blockchain-academic-credentials","source":"GitHub","vertical":"credential","term":"verifiable-credentials","w":5,"ms":1784197035000,"eng":0,"url":"https://github.com/gennarodambrosio-hub/blockchain-academic-credentials","desc":"Permissioned blockchain for verifiable academic credentials — PKI, Merkle-proof selective disclosure, Tendermint-style BFT consensus and TLS 1.3 simulation (Security course project)","author":"gennarodambrosio-hub","company":"Gennaro D' Ambrosio","website":null,"score":84,"first_seen":1784236521706,"last_seen":1784236521706},{"id":"gh_1290009057","name":"luisgf/openvc","source":"GitHub","vertical":"credential","term":"verifiable-credentials","w":5,"ms":1784189487000,"eng":1,"url":"https://github.com/luisgf/openvc","desc":"Generic, HSM-friendly Verifiable Credentials core — VC-JWT and Data Integrity proofs, DID resolution (key/web/ebsi), status lists — with an optional read-only EBSI plugin.","author":"luisgf","company":"Luis González Fernández","website":"Http://www.luisgf.es","score":84,"first_seen":1784236521706,"last_seen":1784236521706},{"id":"gh_1225944207","name":"quarkiverse/quarkus-verifiable-credentials","source":"GitHub","vertical":"credential","term":"verifiable-credentials","w":5,"ms":1784151100000,"eng":1,"url":"https://github.com/quarkiverse/quarkus-verifiable-credentials","desc":"Facilitates verification of Verifiable Presentations","author":"quarkiverse","company":"Quarkiverse Hub","website":"https://quarkiverse.io","score":84,"first_seen":1784236521706,"last_seen":1784236521706},{"id":"gh_1266542347","name":"eudi-verify/eudi-verify","source":"GitHub","vertical":"credential","term":"verifiable-credentials","w":5,"ms":1784139472000,"eng":0,"url":"https://github.com/eudi-verify/eudi-verify","desc":"Framework-agnostic EUDI Wallet verifier kit: web component, typed client SDK, optional React wrapper, Node handlers, OpenAPI - with HTML, React, and Vue reference examples.","author":"eudi-verify","website":null,"score":84,"first_seen":1784236521706,"last_seen":1784236521706},{"id":"gh_951969662","name":"affinidi/affinidi-ssi-dart","source":"GitHub","vertical":"credential","term":"ssi","w":5,"ms":1784101686000,"eng":8,"url":"https://github.com/affinidi/affinidi-ssi-dart","desc":"SSI library for dart","author":"affinidi","company":"Affinidi","website":"www.affinidi.com","score":84,"first_seen":1784236521706,"last_seen":1784236521706},{"id":"hire_sofi","name":"Sofi","source":"Hiring","company":"Sofi","vertical":"identity","term":"hiring: Fraud Strategist - Ecosystem","w":4,"ms":1784141699000,"eng":120,"url":"https://sofi.com/careers/job/7789709003?gh_jid=7789709003","desc":"Open roles: Fraud Strategist - Ecosystem · Fraud Strategist - Login and Auth · Staff Fraud Analyst · Credit Risk Oversight Manager (2LOD)","author":"Sofi","score":84,"first_seen":1784236521706,"last_seen":1784236521706},{"id":"hire_gemini","name":"Gemini","source":"Hiring","company":"Gemini","vertical":"identity","term":"hiring: Analyst, Compliance (Investigations)","w":4,"ms":1784148795000,"eng":120,"url":"https://boards.greenhouse.io/embed/job_app?for=gemini&token=8065112&gh_jid=8065112","desc":"Open roles: Analyst, Compliance (Investigations) · Director, Fraud · Head of Compliance, Gemini Galactic Markets, LLC · Manager, Compliance (Banking & Lending)","author":"Gemini","score":84,"first_seen":1784236521706,"last_seen":1784236521706},{"id":"hire_ebury","name":"Ebury","source":"Hiring","company":"Ebury","vertical":"identity","term":"hiring: Compliance Manager ","w":4,"ms":1784182977000,"eng":120,"url":"https://job-boards.eu.greenhouse.io/ebury/jobs/4928932101","desc":"Open roles: Compliance Manager  · Compliance Officer & MLRO  · Junior KYC Onboarding Analyst · KYC Onboarding Analyst","author":"Ebury","score":84,"first_seen":1784236521706,"last_seen":1784236521706},{"id":"gh_645773754","name":"hyperledger-identus/mediator","source":"GitHub","vertical":"credential","term":"ssi","w":5,"ms":1784000752000,"eng":21,"url":"https://github.com/hyperledger-identus/mediator","desc":"Identus DIDComm V2 Mediator","author":"hyperledger-identus","company":"Hyperledger Identus","website":"https://www.lfdecentralizedtrust.org/","score":83,"first_seen":1784236521706,"last_seen":1784236521706},{"id":"gh_870738438","name":"spruceid/sprucekit-mobile","source":"GitHub","vertical":"credential","term":"ssi","w":5,"ms":1784050737000,"eng":16,"url":"https://github.com/spruceid/sprucekit-mobile","desc":"Libraries and examples for integrating verifiable credentials (VC) and mobile driver's licenses (mDL) into mobile apps.","author":"spruceid","company":"SpruceID","website":"https://spruceid.com","score":83,"first_seen":1784236521706,"last_seen":1784236521706},{"id":"hire_stripe","name":"Stripe","source":"Hiring","company":"Stripe","vertical":"identity","term":"hiring: Chief Compliance Officer (APAC)","w":4,"ms":1784130659000,"eng":120,"url":"https://stripe.com/jobs/search?gh_jid=8023529","desc":"Open roles: Chief Compliance Officer (APAC) · Compliance and Anti Money Laundering Officer — French Branch · Compliance Manager, User Enablement · Employee Relations & HR Compliance Specialist","author":"Stripe","score":83,"first_seen":1784236521706,"last_seen":1784236521706},{"id":"hire_gocardless","name":"Gocardless","source":"Hiring","company":"Gocardless","vertical":"identity","term":"hiring: Financial Crime Risk Manager - 12 month FTC","w":4,"ms":1784096087000,"eng":120,"url":"https://job-boards.greenhouse.io/gocardless/jobs/8048176","desc":"Open roles: Financial Crime Risk Manager - 12 month FTC · Fraud Investigations Specialist · Fraud Investigator (12-month FTC) · Regulatory Compliance Associate","author":"Gocardless","score":83,"first_seen":1784236521706,"last_seen":1784236521706},{"id":"hire_payoneer","name":"Payoneer","source":"Hiring","company":"Payoneer","vertical":"identity","term":"hiring: Compliance Review Analyst","w":4,"ms":1784105413000,"eng":120,"url":"https://www.payoneer.com/careers/position/8020539/?gh_jid=8020539","desc":"Open roles: Compliance Review Analyst · Compliance Training Specialist · Director of KYC Strategy · KYC Representative","author":"Payoneer","score":83,"first_seen":1784236521706,"last_seen":1784236521706},{"id":"gh_1273643506","name":"moisesja/credentials-dotnet","source":"GitHub","vertical":"credential","term":"ssi","w":5,"ms":1784032954000,"eng":0,"url":"https://github.com/moisesja/credentials-dotnet","desc":".NET library that implements the W3C Verifiable Credentials Data Model 2.0 (VCDM 2.0) — creating, issuing, holding, presenting, and verifying Verifiable Credentials (VCs) and Verifiable Presentations (VPs). A VC is a tamper-evident, cryptographically secured set of claims made by an issuer eg. a diploma or licence.","author":"moisesja","company":"Moises E Jaramillo","website":"https://www.linkedin.com/in/moisesjaramillo/","score":82,"first_seen":1784236521706,"last_seen":1784236521706},{"id":"gh_510142714","name":"FabioPinheiro/scala-did","source":"GitHub","vertical":"credential","term":"ssi","w":5,"ms":1783987211000,"eng":9,"url":"https://github.com/FabioPinheiro/scala-did","desc":"A Scala & Scala.js implementation of DID and DID Comm messaging spec","author":"FabioPinheiro","company":"Fabio Pinheiro","website":"https://www.fmgp.app","score":82,"first_seen":1784236521706,"last_seen":1784236521706},{"id":"hire_chime","name":"Chime","source":"Hiring","company":"Chime","vertical":"identity","term":"hiring: Senior Associate, Business Compliance","w":4,"ms":1784052703000,"eng":120,"url":"https://boards.greenhouse.io/chime/jobs/8440967002?gh_jid=8440967002","desc":"Open roles: Senior Associate, Business Compliance · Senior Associate, Product Compliance · Senior Analyst, Financial Crimes & Identity Quality · Software Engineer, Credit Risk Platform","author":"Chime","score":82,"first_seen":1784236521706,"last_seen":1784236521706},{"id":"hire_robinhood","name":"Robinhood","source":"Hiring","company":"Robinhood","vertical":"identity","term":"hiring: Crypto Product Compliance Lead","w":4,"ms":1784066286000,"eng":120,"url":"https://boards.greenhouse.io/robinhood/jobs/7976912?t=gh_src=&gh_jid=7976912","desc":"Open roles: Crypto Product Compliance Lead · Crypto Product Compliance Lead · Product Compliance Analyst, Money · Risk and Compliance Manager","author":"Robinhood","score":82,"first_seen":1784236521706,"last_seen":1784236521706},{"id":"hire_coinbase","name":"Coinbase","source":"Hiring","company":"Coinbase","vertical":"identity","term":"hiring: AMLCO & Senior Compliance Associate","w":4,"ms":1784050332000,"eng":120,"url":"https://www.coinbase.com/careers/positions/7942306?gh_jid=7942306","desc":"Open roles: AMLCO & Senior Compliance Associate · Compliance, Threat & Risk Assessment Manager · Group Product Manager, Compliance Agent Experience · Group Product Manager, Compliance Automation","author":"Coinbase","score":82,"first_seen":1784236521706,"last_seen":1784236521706},{"id":"hire_bvnk","name":"Bvnk","source":"Hiring","company":"Bvnk","vertical":"identity","term":"hiring:  Financial Crime & Compliance Product Manager ","w":4,"ms":1784034068000,"eng":120,"url":"https://job-boards.eu.greenhouse.io/bvnk/jobs/4854112101","desc":"Open roles:  Financial Crime & Compliance Product Manager  · Head of Compliance - US · Tech Lead (Backend): Fraud · Senior Onboarding Analyst","author":"Bvnk","score":82,"first_seen":1784236521706,"last_seen":1784236521706},{"id":"hire_tamara","name":"Tamara","source":"Hiring","company":"Tamara","vertical":"identity","term":"hiring: AML Transaction Monitoring Ops - Builders Program - (Emirati National)","w":4,"ms":1784020764000,"eng":120,"url":"https://job-boards.eu.greenhouse.io/tamara/jobs/4849504101","desc":"Open roles: AML Transaction Monitoring Ops - Builders Program - (Emirati National) · Compliance Associate - Builders Program - (Emirati National) · Fraud Investigator · Fraud Risk Analyst ","author":"Tamara","score":82,"first_seen":1784236521706,"last_seen":1784236521706},{"id":"gh_1275479855","name":"zentto-erp/zentto-web3-mobile","source":"GitHub","vertical":"identity","term":"KYC / identity","w":5,"ms":1783949597000,"eng":0,"url":"https://github.com/zentto-erp/zentto-web3-mobile","desc":"App movil (Ionic React + Capacitor) de usuario final del servicio cripto custodial Zentto: enviar/recibir, recargar, P2P USDT/USDC vs VES, KYC y 2FA.","author":"zentto-erp","company":"Zentto ERP","website":"https://zentto.net","score":81,"first_seen":1784236521706,"last_seen":1784236521706},{"id":"hire_bybit","name":"Bybit","source":"Hiring","company":"Bybit","vertical":"identity","term":"hiring: Compliance & AML Lead, Hong Kong","w":4,"ms":1783978891000,"eng":120,"url":"https://job-boards.eu.greenhouse.io/bybit/jobs/4860962101","desc":"Open roles: Compliance & AML Lead, Hong Kong · Fraud Prevention Investigation Lead · Global Talent Acquisition Lead/ Expert (Legal & Compliance) · Head of Compliance, EU","author":"Bybit","score":81,"first_seen":1784236521706,"last_seen":1784236521706},{"id":"hire_inter","name":"Inter","source":"Hiring","company":"Inter","vertical":"identity","term":"hiring: COMPLIANCE ANALYST III - REGULATORY COMPLIANCE","w":4,"ms":1783973532000,"eng":120,"url":"https://boards.greenhouse.io/inter/jobs/4694668005?gh_jid=4694668005","desc":"Open roles: COMPLIANCE ANALYST III - REGULATORY COMPLIANCE · US COMPLIANCE ANALYST II (Consumer, Product and Training) · OPERATIONAL RISK & INTERNAL CONTROLS ANALYST III · OPERATIONAL RISK & INTERNAL CONTROLS ASSISTANT","author":"Inter","score":81,"first_seen":1784236521706,"last_seen":1784236521706},{"id":"hn_48889492","name":"Shopify introduces ID verification for Shopify Partners","source":"Hacker News","company":"shopify","vertical":"identity","term":"KYC / identity","w":5,"ms":1783930986000,"eng":2,"url":"https://shopify.dev/changelog/identity-verification-for-partners","author":"jam3sn","score":80,"first_seen":1784236521706,"last_seen":1784236521706},{"id":"gh_189886957","name":"Spoje-NET/php-abraflexi","source":"GitHub","vertical":"fintech","term":"fintech","w":4,"ms":1784236214000,"eng":24,"url":"https://github.com/Spoje-NET/php-abraflexi","desc":"PHP Library for easy interaction with economic system AbraFlexi. ","author":"Spoje-NET","company":"SPOJE.NET s.r.o.","website":"http://spoje.net/","score":78,"first_seen":1784236521706,"last_seen":1784236521706},{"id":"gh_639155694","name":"Yengas/openpgp-did","source":"GitHub","vertical":"credential","term":"ssi","w":5,"ms":1783771961000,"eng":6,"url":"https://github.com/Yengas/openpgp-did","desc":"A CLI tool enabling DID/SSI operations with your OpenPGP smart card","author":"Yengas","company":"Yiğitcan UÇUM","website":"https://yigitcan.dev","score":78,"first_seen":1784236521706,"last_seen":1784236521706},{"id":"gh_1033839539","name":"RemiZlatinis/ssi-agent","source":"GitHub","vertical":"credential","term":"ssi","w":5,"ms":1783759936000,"eng":0,"url":"https://github.com/RemiZlatinis/ssi-agent","desc":"This is the Agent component of the Service Status Indicator monitoring system","author":"RemiZlatinis","company":"Remi","website":null,"score":78,"first_seen":1784236521706,"last_seen":1784236521706},{"id":"gh_1265053402","name":"moisesja/crypto-dotnet","source":"GitHub","vertical":"credential","term":"ssi","w":5,"ms":1783741204000,"eng":0,"url":"https://github.com/moisesja/crypto-dotnet","desc":"A .NET 10 unified cryptographic primitives library stack: EdDSA, ECDSA (NIST curves and secp256k1, including recoverable), BLS12-381, BBS selective-disclosure signatures, X25519/ECDH, KDFs, AEADs, hashing (including Keccak-256), a key model with multibase/multicodec encoding, signing and key-store abstractions, and JWK conversion","author":"moisesja","company":"Moises E Jaramillo","website":"https://www.linkedin.com/in/moisesjaramillo/","score":77,"first_seen":1784236521706,"last_seen":1784236521706},{"id":"hire_mercury","name":"Mercury","source":"Hiring","company":"Mercury","vertical":"identity","term":"hiring: Counsel, Product & Regulatory - Payments & AML","w":4,"ms":1783728780000,"eng":120,"url":"https://job-boards.greenhouse.io/mercury/jobs/6103801004","desc":"Open roles: Counsel, Product & Regulatory - Payments & AML · Financial Crimes Compliance Modeling & Analytics Manager · Senior People Partner - Legal, Compliance, & Risk · Senior Risk Strategist - Card Fraud","author":"Mercury","score":77,"first_seen":1784236521706,"last_seen":1784236521706},{"id":"hire_ripple","name":"Ripple","source":"Hiring","company":"Ripple","vertical":"identity","term":"hiring: Compliance Manager (AML_CFT Compliance Officer) Brazil","w":4,"ms":1783706418000,"eng":120,"url":"https://ripple.com/careers/all-jobs/job/7750354?gh_jid=7750354","desc":"Open roles: Compliance Manager (AML_CFT Compliance Officer) Brazil · Regulatory Compliance Analyst · Professional Services Consultant, Risk · Professional Services Consultant, Risk","author":"Ripple","score":77,"first_seen":1784236521706,"last_seen":1784236521706},{"id":"hire_adyen","name":"Adyen","source":"Hiring","company":"Adyen","vertical":"identity","term":"hiring: APAC Lead - Payment Method Compliance","w":4,"ms":1783709063000,"eng":120,"url":"https://job-boards.greenhouse.io/adyen/jobs/7556224","desc":"Open roles: APAC Lead - Payment Method Compliance · CDD Risk Analyst · CDD Risk Analyst, Direct Customer Onboarding · CDD Risk Analyst, Onboarding","author":"Adyen","score":77,"first_seen":1784236521706,"last_seen":1784236521706},{"id":"gh_1056683419","name":"ab20032002/qwed-finance","source":"GitHub","vertical":"identity","term":"kyc","w":5,"ms":1784235529000,"eng":0,"url":"https://github.com/ab20032002/qwed-finance","desc":"🏦 Enhance banking and financial AI with QWED-Finance, a middleware that ensures deterministic verification for reliable decision-making.","author":"ab20032002","website":null,"score":76,"first_seen":1784236521706,"last_seen":1784236521706},{"id":"gh_1224647855","name":"soledadpepsin39/NeoBank-Chain","source":"GitHub","vertical":"fintech","term":"neobank","w":4,"ms":1784230556000,"eng":0,"url":"https://github.com/soledadpepsin39/NeoBank-Chain","desc":"Build a blockchain banking super-app for IBAN, DeFi, ethical finance, and AI-powered money management on Solana","author":"soledadpepsin39","website":null,"score":76,"first_seen":1784236521706,"last_seen":1784236521706},{"id":"gh_1174075019","name":"bigvaldis/breaking_news_market_sentiment","source":"GitHub","vertical":"fintech","term":"fintech","w":4,"ms":1784236525000,"eng":2,"url":"https://github.com/bigvaldis/breaking_news_market_sentiment","desc":"Analyze breaking news to track market sentiment, classify articles, and link insights to financial indicators in real time.","author":"bigvaldis","website":null,"score":76,"first_seen":1784236521706,"last_seen":1784236521706},{"id":"gh_1206952867","name":"timode-6/api-gateway","source":"GitHub","vertical":"fintech","term":"fintech","w":4,"ms":1784236305000,"eng":0,"url":"https://github.com/timode-6/api-gateway","desc":"Serves as a centralized entry point for routing, authentication, and traffic management","author":"timode-6","website":null,"score":76,"first_seen":1784236521706,"last_seen":1784236521706},{"id":"gh_551034963","name":"WalletInc/sdk-python","source":"GitHub","vertical":"fintech","term":"fintech","w":4,"ms":1784236289000,"eng":0,"url":"https://github.com/WalletInc/sdk-python","desc":"Python SDK to interact with Wallet API","author":"WalletInc","company":"Wallet Inc.","website":"https://wallet.inc/github","score":76,"first_seen":1784236521706,"last_seen":1784236521706},{"id":"gh_652247765","name":"churst90/accessible-trade-terminal","source":"GitHub","vertical":"fintech","term":"fintech","w":4,"ms":1784236287000,"eng":1,"url":"https://github.com/churst90/accessible-trade-terminal","desc":"A unique .NET 10 MAUI Blazor Hybrid terminal for accessible trading. Key pillars include a low-latency C# audio engine, universal keyboard navigation, and native screen reader speech integration. Features a robust provider architecture supporting 24+ data sources and a custom plugin provider/indicator platform.","author":"churst90","website":null,"score":76,"first_seen":1784236521706,"last_seen":1784236521706},{"id":"gh_550879090","name":"WalletInc/sdk-ts","source":"GitHub","vertical":"fintech","term":"fintech","w":4,"ms":1784236223000,"eng":2,"url":"https://github.com/WalletInc/sdk-ts","desc":"TypeScript SDK (server side) to interact with Wallet API: https://wallet.dev","author":"WalletInc","company":"Wallet Inc.","website":"https://wallet.inc/github","score":76,"first_seen":1784236521706,"last_seen":1784236521706},{"id":"gh_992119717","name":"Nightizi/Bradesco---GenAI-Dados-Projeto-1","source":"GitHub","vertical":"fintech","term":"fintech","w":4,"ms":1784236208000,"eng":1,"url":"https://github.com/Nightizi/Bradesco---GenAI-Dados-Projeto-1","desc":"📊 Develop data-driven AI solutions for banking insights through Bradesco's GenAI Dados bootcamp project.","author":"Nightizi","company":"God","website":"https://biolink.info/esilva.024","score":76,"first_seen":1784236521706,"last_seen":1784236521706},{"id":"gh_1168352637","name":"cristianmacbook0-netizen/quantds","source":"GitHub","vertical":"fintech","term":"fintech","w":4,"ms":1784236208000,"eng":1,"url":"https://github.com/cristianmacbook0-netizen/quantds","desc":"📊 Provide unified, multi-market financial data access with failover, caching, and support for stocks, funds, and bonds across major sources.","author":"cristianmacbook0-netizen","website":null,"score":76,"first_seen":1784236521706,"last_seen":1784236521706},{"id":"gh_917949925","name":"nikhilambhure01/aurumpulse","source":"GitHub","vertical":"fintech","term":"fintech","w":4,"ms":1784236110000,"eng":0,"url":"https://github.com/nikhilambhure01/aurumpulse","desc":"💰 Deliver real-time 24K gold price alerts and daily updates via WhatsApp with AurumPulse, no app installation needed.","author":"nikhilambhure01","website":null,"score":76,"first_seen":1784236521706,"last_seen":1784236521706},{"id":"gh_1122939923","name":"safal207/Causal-Memory-Layer","source":"GitHub","vertical":"fintech","term":"fintech / payments","w":4,"ms":1784236015000,"eng":5,"url":"https://github.com/safal207/Causal-Memory-Layer","desc":"CML (Causal Memory Layer) — a foundational memory layer for recording reasons, permissions, and responsibility behind actions, not just events or results. Enables systems in AI, fintech, security, and distributed computing to preserve meaning and causal accountability across time, independent of execution or transport.","author":"safal207","company":"Aleksey Safonov","website":"https://github.com/safal207/LS","score":76,"first_seen":1784236521706,"last_seen":1784236521706},{"id":"gh_1269178570","name":"s3ntin3l8/pocket-portfolio-tracker","source":"GitHub","vertical":"fintech","term":"fintech","w":4,"ms":1784236046000,"eng":0,"url":"https://github.com/s3ntin3l8/pocket-portfolio-tracker","desc":"Indonesian-first personal portfolio tracker — import transactions from screenshots (LLM vision) & CSV; track IDX equities, gold, bonds, reksa dana & cash with live prices and a real-time gold ticker. Fastify + Next.js PWA monorepo, expandable to Trade Republic.","author":"s3ntin3l8","company":"Björn Hansen","website":null,"score":76,"first_seen":1784236521706,"last_seen":1784236521706},{"id":"gh_1114071543","name":"erfanansari/kharji","source":"GitHub","vertical":"fintech","term":"fintech","w":4,"ms":1784235945000,"eng":3,"url":"https://github.com/erfanansari/kharji","desc":"Multi-currency personal finance PWA with offline support and real-time conversion.","author":"erfanansari","company":"Erfan Ansari","website":"erfanansari.com","score":76,"first_seen":1784236521706,"last_seen":1784236521706},{"id":"gh_1048590122","name":"kimingoood-code/agentic-ai-credit-underwriting","source":"GitHub","vertical":"fintech","term":"fintech","w":4,"ms":1784235921000,"eng":1,"url":"https://github.com/kimingoood-code/agentic-ai-credit-underwriting","desc":null,"author":"kimingoood-code","website":null,"score":76,"first_seen":1784236521706,"last_seen":1784236521706},{"id":"gh_930267319","name":"heydsqi-dsq/cross-border-fraud-detection","source":"GitHub","vertical":"fintech","term":"fintech","w":4,"ms":1784235781000,"eng":0,"url":"https://github.com/heydsqi-dsq/cross-border-fraud-detection","desc":"🛡️ Detect cross-border payment fraud in real-time with a highly accurate API, reducing costly false positives for financial institutions.","author":"heydsqi-dsq","website":null,"score":76,"first_seen":1784236521706,"last_seen":1784236521706},{"id":"gh_1274457084","name":"yoshidai55/stablecoin-guide","source":"GitHub","vertical":"fintech","term":"fintech","w":4,"ms":1784235746000,"eng":0,"url":"https://github.com/yoshidai55/stablecoin-guide","desc":"ステーブルコインの歴史・現状・未来をやさしく学べる学習サイト。市場データはリアルタイム、ニュースは毎日自動更新。","author":"yoshidai55","website":null,"score":76,"first_seen":1784236521706,"last_seen":1784236521706},{"id":"gh_1150982631","name":"ELIEER103/google-account-automanager","source":"GitHub","vertical":"fintech","term":"fintech","w":4,"ms":1784235714000,"eng":2,"url":"https://github.com/ELIEER103/google-account-automanager","desc":"🌐 Automate Google account tasks with FastAPI and Vue 3, including management, 2FA setup, and eligibility checks for efficient batch operations.","author":"ELIEER103","website":null,"score":76,"first_seen":1784236521706,"last_seen":1784236521706},{"id":"gh_1160184165","name":"Nour-Alhendi/AI-Merchant-Intelligence","source":"GitHub","vertical":"fintech","term":"fintech / payments","w":4,"ms":1784235695000,"eng":1,"url":"https://github.com/Nour-Alhendi/AI-Merchant-Intelligence","desc":" Production-style Hybrid Structured + RAG fintech risk analytics system with FastAPI, LLM routing, cross-encoder reranking, and 1M synthetic transactions.","author":"Nour-Alhendi","company":"Nour Al Hendi","website":null,"score":76,"first_seen":1784236521706,"last_seen":1784236521706},{"id":"gh_1303195633","name":"jarueda97/plata-clara","source":"GitHub","vertical":"fintech","term":"fintech","w":4,"ms":1784235606000,"eng":0,"url":"https://github.com/jarueda97/plata-clara","desc":"Subí el extracto de tu banco y mirá cuánto pagaste de verdad en intereses y en suscripciones. Local-first: no hay servidor al cual subirlo. Hecho para Colombia.","author":"jarueda97","website":null,"score":76,"first_seen":1784236521706,"last_seen":1784236521706},{"id":"gh_1146831637","name":"lvanphong/omni-synapse-v2","source":"GitHub","vertical":"fintech","term":"fintech","w":4,"ms":1784235554000,"eng":2,"url":"https://github.com/lvanphong/omni-synapse-v2","desc":"⚡ Accelerate your applications with the next-gen Ultra-Low-Latency Engine, achieving optimized performance with minimal CPU cycles.","author":"lvanphong","website":null,"score":76,"first_seen":1784236521706,"last_seen":1784236521706},{"id":"gh_1144942720","name":"hr6u/fgn-bonds","source":"GitHub","vertical":"fintech","term":"fintech","w":4,"ms":1784235488000,"eng":0,"url":"https://github.com/hr6u/fgn-bonds","desc":"📄 Submit FGN Savings Bond applications easily with this React + FastAPI web app, featuring a 7-step wizard, PDF generation, and payment tracking.","author":"hr6u","website":null,"score":76,"first_seen":1784236521706,"last_seen":1784236521706},{"id":"gh_1303237962","name":"diegogallina1/clinic-finance-dashboard","source":"GitHub","vertical":"fintech","term":"fintech","w":4,"ms":1784235414000,"eng":0,"url":"https://github.com/diegogallina1/clinic-finance-dashboard","desc":"Financial dashboard for small medical practices: receivables, cash-flow projection & automated monthly reports. React + Firebase + Chart.js.","author":"diegogallina1","website":null,"score":76,"first_seen":1784236521706,"last_seen":1784236521706},{"id":"hire_brex","name":"Brex","source":"Hiring","company":"Brex","vertical":"identity","term":"hiring: Compliance Manager, Marketing","w":4,"ms":1783626847000,"eng":120,"url":"https://www.brex.com/careers/8544882002?gh_jid=8544882002","desc":"Open roles: Compliance Manager, Marketing · Compliance Manager, Marketing · Compliance Manager, Marketing · Director, Credit Risk","author":"Brex","score":76,"first_seen":1784236521706,"last_seen":1784236521706},{"id":"hire_monzo","name":"Monzo","source":"Hiring","company":"Monzo","vertical":"identity","term":"hiring: Director of Fraud","w":4,"ms":1783675662000,"eng":120,"url":"https://job-boards.greenhouse.io/monzo/jobs/8002441","desc":"Open roles: Director of Fraud · Fraud Team Manager, English & Spanish Speaking · Credit Risk Director, Business Borrowing · Credit Risk Manager, Portfolio Management","author":"Monzo","score":76,"first_seen":1784236521706,"last_seen":1784236521706},{"id":"hire_n26","name":"N26","source":"Hiring","company":"N26","vertical":"identity","term":"hiring: Manager Banking Compliance","w":4,"ms":1783682153000,"eng":120,"url":"https://n26.com/en-eu/careers/positions/8023334?gh_jid=8023334","desc":"Open roles: Manager Banking Compliance · Backend Engineer - Customer Identity · Backend Engineer - Customer Identity · Backend Engineer - Customer Risk Lifecycle","author":"N26","score":76,"first_seen":1784236521706,"last_seen":1784236521706},{"id":"gh_1287624054","name":"andreolf/neobankbeat","source":"GitHub","vertical":"wallet","term":"wallet","w":4,"ms":1784198710000,"eng":1,"url":"https://github.com/andreolf/neobankbeat","desc":"who watches the neobanks? open-source directory of 357 verified-active neobanks — traditional, hybrid crypto & web3-native — compared on custody, cards, yield, stablecoins & regulation","author":"andreolf","company":"Francesco","website":null,"score":75,"first_seen":1784236521706,"last_seen":1784236521706},{"id":"gh_1266008073","name":"moviendome/solana-rails-neobank","source":"GitHub","vertical":"fintech","term":"fintech / payments","w":4,"ms":1784192909000,"eng":0,"url":"https://github.com/moviendome/solana-rails-neobank","desc":"Lamport — a Neo-bank built on the Solana Developer Platform with Rails 8 + Hotwire. Real devnet custody wallets, P2P transfers with on-chain proof, recurring   payments, realtime balances via Turbo Streams.","author":"moviendome","company":"Jose Ferrer","website":"https://moviendo.me","score":75,"first_seen":1784236521706,"last_seen":1784236521706},{"id":"gh_1084286393","name":"european-epc-competence-center/key-service","source":"GitHub","vertical":"credential","term":"ssi","w":5,"ms":1783517368000,"eng":2,"url":"https://github.com/european-epc-competence-center/key-service","desc":"A cryptographic key service for storing private keys and using them to sign verifiable credentials and presentations","author":"european-epc-competence-center","company":" European EPC Competence Center GmbH (EECC)","website":"https://www.eecc.de","score":74,"first_seen":1784236521706,"last_seen":1784236521706},{"id":"hire_bitpanda","name":"Bitpanda","source":"Hiring","company":"Bitpanda","vertical":"identity","term":"hiring: Senior Specialist, AML","w":4,"ms":1783492763000,"eng":120,"url":"https://job-boards.eu.greenhouse.io/bitpanda/jobs/4914393101","desc":"Open roles: Senior Specialist, AML · Team Lead, Regulatory Compliance · Senior Software Engineer, Java (Regulatory Onboarding) · Specialist, Payment & Risk Operations ","author":"Bitpanda","score":74,"first_seen":1784236521706,"last_seen":1784236521706},{"id":"hire_c6bank","name":"C6bank","source":"Hiring","company":"C6bank","vertical":"identity","term":"hiring: Auxiliar Administrativo de Operações | Onboarding | Vaga Afirmativa para Pessoas com Deficiência","w":4,"ms":1783949829000,"eng":30,"url":"https://job-boards.greenhouse.io/c6bank/jobs/4704955005","desc":"Open roles: Auxiliar Administrativo de Operações | Onboarding | Vaga Afirmativa para Pessoas com Deficiência","author":"C6bank","score":74,"first_seen":1784236521706,"last_seen":1784236521706},{"id":"code_tsiemasilo-dev","name":"tsiemasilo-dev/MINT-LIVE","source":"Building with","vertical":"identity","term":"uses Sumsub","w":4,"ms":1784106047000,"eng":0,"url":"https://github.com/tsiemasilo-dev/MINT-LIVE","desc":"Ships the Sumsub SDK in production code (tsiemasilo-dev/MINT-LIVE)","company":"tsiemasilo-dev","website":null,"author":"tsiemasilo-dev","vendor":"Sumsub","score":74,"first_seen":1784236521706,"last_seen":1784236521706},{"id":"gh_430623498","name":"Sphereon-Opensource/SSI-SDK","source":"GitHub","vertical":"credential","term":"ssi","w":5,"ms":1783088614000,"eng":75,"url":"https://github.com/Sphereon-Opensource/SSI-SDK","desc":"(Legacy) Self Sovereign Identity SDK","author":"Sphereon-Opensource","company":"Sphereon Open Source","website":"https://sphereon.com","score":73,"first_seen":1784236521706,"last_seen":1784236521706},{"id":"hire_affirm","name":"Affirm","source":"Hiring","company":"Affirm","vertical":"identity","term":"hiring: Affirm Bank Compliance Lead, CRA and Complaints","w":4,"ms":1783465417000,"eng":120,"url":"https://job-boards.greenhouse.io/affirm/jobs/7752003003","desc":"Open roles: Affirm Bank Compliance Lead, CRA and Complaints · Analyst II, Full Stack (Fraud Analytics) · Compliance Analyst I · Compliance Lead, Canada","author":"Affirm","score":73,"first_seen":1784236521706,"last_seen":1784236521706},{"id":"hire_checkr","name":"Checkr","source":"Hiring","company":"Checkr","vertical":"identity","term":"hiring: Senior Staff Product Manager, Fraud Hiring Solutions","w":4,"ms":1783607133000,"eng":90,"url":"https://job-boards.greenhouse.io/checkr/jobs/7894772","desc":"Open roles: Senior Staff Product Manager, Fraud Hiring Solutions · Staff Product Manager, Hiring Fraud Solutions · Income Verification QA Analyst, Truework","author":"Checkr","score":73,"first_seen":1784236521706,"last_seen":1784236521706},{"id":"hire_okx","name":"Okx","source":"Hiring","company":"Okx","vertical":"identity","term":"hiring: Compliance Lead, Compliance & Ethics","w":4,"ms":1783458518000,"eng":120,"url":"https://job-boards.greenhouse.io/okx/jobs/7798187003","desc":"Open roles: Compliance Lead, Compliance & Ethics · Director, Compliance Data Science & AI · Director, Compliance Data Science & AI · Fraud Risk Strategy Expert","author":"Okx","score":73,"first_seen":1784236521706,"last_seen":1784236521706},{"id":"hire_block","name":"Block","source":"Hiring","company":"Block","vertical":"identity","term":"hiring: Compliance Operations Specialist, JP","w":4,"ms":1783385655000,"eng":120,"url":"http://block.xyz/careers/jobs/5125397008?gh_jid=5125397008","desc":"Open roles: Compliance Operations Specialist, JP · Compliance Technology Program Lead · Staff Applied Machine Learning Engineer - Fraud & Abuse · Staff Data Analyst, Block Compliance","author":"Block","score":72,"first_seen":1784236521706,"last_seen":1784236521706},{"id":"hire_sumup","name":"Sumup","source":"Hiring","company":"Sumup","vertical":"identity","term":"hiring: AML Analyst ll","w":4,"ms":1783365315000,"eng":120,"url":"https://sumup.com/careers/positions/8596506002?gh_jid=8596506002","desc":"Open roles: AML Analyst ll · Compliance Operations Analyst with Italian · Fraud Prevention Agent II · Fraud Prevention Manager","author":"Sumup","score":72,"first_seen":1784236521706,"last_seen":1784236521706},{"id":"code_ratio1","name":"Ratio1/ratio1-dapp","source":"Building with","vertical":"identity","term":"uses Sumsub","w":6,"ms":1782724856000,"eng":0,"url":"https://github.com/Ratio1/ratio1-dapp","desc":"Ships the Sumsub SDK in production code (Ratio1/ratio1-dapp)","company":"Ratio1.ai","website":"ratio1.ai","author":"ratio1","vendor":"Sumsub","score":71,"first_seen":1784236521706,"last_seen":1784236521706},{"id":"gh_1228126215","name":"VirInvictus/opends","source":"GitHub","vertical":"credential","term":"ssi","w":5,"ms":1783295423000,"eng":0,"url":"https://github.com/VirInvictus/opends","desc":"Open community toolkit and bugfix patches for SSI's Dark Sun CRPGs (Shattered Lands, Wake of the Ravager): decoded formats, a round-trippable GFF editor, and a GPL bytecode assembler/disassembler. Bring your own game data.","author":"VirInvictus","company":"Brandon LaRocque","website":null,"score":70,"first_seen":1784236521706,"last_seen":1784236521706},{"id":"gh_1284157336","name":"identra-awncorp/identra-app","source":"GitHub","vertical":"credential","term":"ssi","w":5,"ms":1783124800000,"eng":0,"url":"https://github.com/identra-awncorp/identra-app","desc":null,"author":"identra-awncorp","website":null,"score":68,"first_seen":1784236521706,"last_seen":1784236521706},{"id":"code_devasignhq","name":"devasignhq/apps","source":"Building with","vertical":"identity","term":"uses Sumsub","w":6,"ms":1782491958000,"eng":6,"url":"https://github.com/devasignhq/apps","desc":"Ships the Sumsub SDK in production code (devasignhq/apps)","company":"DevAsign","website":"https://devasign.com","author":"devasignhq","vendor":"Sumsub","score":68,"first_seen":1784236521706,"last_seen":1784236521706},{"id":"hire_solarisbank","name":"Solarisbank","source":"Hiring","company":"Solarisbank","vertical":"identity","term":"hiring: KYC Operations Working Student (f/m/d) ","w":4,"ms":1783067921000,"eng":120,"url":"https://job-boards.greenhouse.io/solarisbank/jobs/8514915002","desc":"Open roles: KYC Operations Working Student (f/m/d)  · Senior Compliance Specialist (f/m/d) · Credit Risk Manager (f/m/d) · Risk Controlling Manager (f/m/d)","author":"Solarisbank","score":67,"first_seen":1784236521706,"last_seen":1784236521706},{"id":"hn_48618455","name":"Identity verification on Claude","source":"Hacker News","company":"support","vertical":"identity","term":"KYC / identity","w":5,"ms":1782045853000,"eng":2338,"url":"https://support.claude.com/en/articles/14328960-identity-verification-on-claude","author":"bathory","score":66,"first_seen":1784236521706,"last_seen":1784236521706},{"id":"hire_xendit","name":"Xendit","source":"Hiring","company":"Xendit","vertical":"identity","term":"hiring: Regulatory Compliance and AML Manager","w":4,"ms":1783063643000,"eng":90,"url":"https://job-boards.greenhouse.io/xendit/jobs/7683511003","desc":"Open roles: Regulatory Compliance and AML Manager · Regulatory Compliance and AML Manager · Product Manager – Risk Products","author":"Xendit","score":65,"first_seen":1784236521706,"last_seen":1784236521706},{"id":"hire_lithic","name":"Lithic","source":"Hiring","company":"Lithic","vertical":"identity","term":"hiring: Senior AML Analyst","w":4,"ms":1783023820000,"eng":60,"url":"https://job-boards.greenhouse.io/lithic/jobs/6104066004","desc":"Open roles: Senior AML Analyst · Senior Compliance Analyst","author":"Lithic","score":62,"first_seen":1784236521706,"last_seen":1784236521706},{"id":"hire_marqeta","name":"Marqeta","source":"Hiring","company":"Marqeta","vertical":"identity","term":"hiring: Credit Risk Manager","w":4,"ms":1782749098000,"eng":120,"url":"https://job-boards.greenhouse.io/marqeta/jobs/7859828","desc":"Open roles: Credit Risk Manager · Credit Risk Senior Manager · Manager, Software Engineering - Identity Platform · Manager, Software Engineering - Identity Platform","author":"Marqeta","score":62,"first_seen":1784236521706,"last_seen":1784236521706},{"id":"hire_thunes","name":"Thunes","source":"Hiring","company":"Thunes","vertical":"identity","term":"hiring: Compliance Manager","w":4,"ms":1782726696000,"eng":120,"url":"https://www.thunes.com/jobs/7784643003?gh_jid=7784643003","desc":"Open roles: Compliance Manager ·  Fraud Risk Manager · KYC Officer · KYC Officer","author":"Thunes","score":62,"first_seen":1784236521706,"last_seen":1784236521706},{"id":"code_buyownex","name":"BuyOwnEx/BOEClient","source":"Building with","vertical":"identity","term":"uses Sumsub","w":4,"ms":1783027184000,"eng":31,"url":"https://github.com/BuyOwnEx/BOEClient","desc":"Ships the Sumsub SDK in production code (BuyOwnEx/BOEClient)","company":"BuyOwnEx","website":"https://buyownex.com","author":"buyownex","vendor":"Sumsub","score":60,"first_seen":1784236521706,"last_seen":1784236521706},{"id":"gh_1141408294","name":"Ad-Infinitum-Corp/Infinite","source":"GitHub","vertical":"fintech","term":"neobank","w":4,"ms":1783128365000,"eng":1,"url":"https://github.com/Ad-Infinitum-Corp/Infinite","desc":"Global banking for Everyone!  Infinite Corporation","author":"Ad-Infinitum-Corp","company":"Ad Infinitum ","website":"ad-infinitum.xyz","score":59,"first_seen":1784236521706,"last_seen":1784236521706},{"id":"gh_1274771547","name":"zentto-erp/zentto-web3","source":"GitHub","vertical":"identity","term":"KYC / identity","w":5,"ms":1782409087000,"eng":0,"url":"https://github.com/zentto-erp/zentto-web3","desc":"Core bancario de un neobanco cripto custodial: API NestJS con ledger de doble entrada, depositos/retiros on-chain (EVM/Tron/Solana), KYC/AML, P2P con escrow y 2FA.","author":"zentto-erp","company":"Zentto ERP","website":"https://zentto.net","score":57,"first_seen":1784236521706,"last_seen":1784236521706},{"id":"code_consensys","name":"Consensys/codefi-assets-and-payments","source":"Building with","vertical":"identity","term":"uses Onfido","w":6,"ms":1778510993000,"eng":22,"url":"https://github.com/Consensys/codefi-assets-and-payments","desc":"Ships the Onfido SDK in production code (Consensys/codefi-assets-and-payments)","company":"Consensys","website":"https://www.consensys.io","author":"consensys","vendor":"Onfido","score":56,"first_seen":1784236521706,"last_seen":1784236521706},{"id":"code_dacadeorg","name":"dacadeorg/dacade-frontend-app","source":"Building with","vertical":"identity","term":"uses Sumsub","w":6,"ms":1743780966000,"eng":12,"url":"https://github.com/dacadeorg/dacade-frontend-app","desc":"Ships the Sumsub SDK in production code (dacadeorg/dacade-frontend-app)","company":"dacade","website":"https://dacade.org/","author":"dacadeorg","vendor":"Sumsub","score":55,"first_seen":1784236521706,"last_seen":1784236521706},{"id":"code_worbli","name":"worbli/website","source":"Building with","vertical":"identity","term":"uses Onfido","w":6,"ms":1776248916000,"eng":1,"url":"https://github.com/worbli/website","desc":"Ships the Onfido SDK in production code (worbli/website)","company":"Worbli","website":"worbli.io","author":"worbli","vendor":"Onfido","score":54,"first_seen":1784236521706,"last_seen":1784236521706},{"id":"code_wso2-extensions","name":"wso2-extensions/identity-verification-onfido","source":"Building with","vertical":"identity","term":"uses Onfido","w":6,"ms":1772613234000,"eng":0,"url":"https://github.com/wso2-extensions/identity-verification-onfido","desc":"Ships the Onfido SDK in production code (wso2-extensions/identity-verification-onfido)","company":"WSO2 Extensions","website":"http://wso2.com/","author":"wso2-extensions","vendor":"Onfido","score":54,"first_seen":1784236521706,"last_seen":1784236521706},{"id":"code_asgardeo-samples","name":"asgardeo-samples/bank-of-asgard","source":"Building with","vertical":"identity","term":"uses Onfido","w":6,"ms":1766355138000,"eng":0,"url":"https://github.com/asgardeo-samples/bank-of-asgard","desc":"Ships the Onfido SDK in production code (asgardeo-samples/bank-of-asgard)","company":"Asgardeo Samples","website":"https://wso2.com/asgardeo","author":"asgardeo-samples","vendor":"Onfido","score":54,"first_seen":1784236521706,"last_seen":1784236521706},{"id":"code_holonym-foundation","name":"holonym-foundation/zk-frontend","source":"Building with","vertical":"identity","term":"uses Onfido","w":6,"ms":1739821921000,"eng":6,"url":"https://github.com/holonym-foundation/zk-frontend","desc":"Ships the Onfido SDK in production code (holonym-foundation/zk-frontend)","company":"holonym-foundation","website":null,"author":"holonym-foundation","vendor":"Onfido","score":54,"first_seen":1784236521706,"last_seen":1784236521706},{"id":"code_remittease-dev-team","name":"RemittEase-Dev-Team/RemittEase","source":"Building with","vertical":"identity","term":"uses Onfido","w":6,"ms":1751995179000,"eng":0,"url":"https://github.com/RemittEase-Dev-Team/RemittEase","desc":"Ships the Onfido SDK in production code (RemittEase-Dev-Team/RemittEase)","company":"RemittEase Dev Team","website":null,"author":"remittease-dev-team","vendor":"Onfido","score":54,"first_seen":1784236521706,"last_seen":1784236521706},{"id":"code_vaultov-protocol","name":"vaultov-protocol/vaultov","source":"Building with","vertical":"identity","term":"uses Sumsub","w":6,"ms":1774800093000,"eng":4,"url":"https://github.com/vaultov-protocol/vaultov","desc":"Ships the Sumsub SDK in production code (vaultov-protocol/vaultov)","company":"Vaultov protocol","website":null,"author":"vaultov-protocol","vendor":"Sumsub","score":54,"first_seen":1784236521706,"last_seen":1784236521706},{"id":"code_coinbytep2p","name":"coinbytep2p/coinbyteP2P","source":"Building with","vertical":"identity","term":"uses Sumsub","w":6,"ms":1748464900000,"eng":0,"url":"https://github.com/coinbytep2p/coinbyteP2P","desc":"Ships the Sumsub SDK in production code (coinbytep2p/coinbyteP2P)","company":"coinbytep2p","website":null,"author":"coinbytep2p","vendor":"Sumsub","score":54,"first_seen":1784236521706,"last_seen":1784236521706},{"id":"code_landshare-io","name":"Landshare-io/LS_Frontend_v2","source":"Building with","vertical":"identity","term":"uses Sumsub","w":6,"ms":1775015499000,"eng":0,"url":"https://github.com/Landshare-io/LS_Frontend_v2","desc":"Ships the Sumsub SDK in production code (Landshare-io/LS_Frontend_v2)","company":"landshare-io","website":null,"author":"landshare-io","vendor":"Sumsub","score":54,"first_seen":1784236521706,"last_seen":1784236521706},{"id":"code_diamondnxt","name":"diamondnxt/diamondnxt","source":"Building with","vertical":"identity","term":"uses Sumsub","w":6,"ms":1741089975000,"eng":0,"url":"https://github.com/diamondnxt/diamondnxt","desc":"Ships the Sumsub SDK in production code (diamondnxt/diamondnxt)","company":"DiamondNXT","website":"https://diamondnxt.com","author":"diamondnxt","vendor":"Sumsub","score":54,"first_seen":1784236521706,"last_seen":1784236521706},{"id":"code_rx-casino","name":"rx-casino/client","source":"Building with","vertical":"identity","term":"uses Sumsub","w":6,"ms":1743692247000,"eng":0,"url":"https://github.com/rx-casino/client","desc":"Ships the Sumsub SDK in production code (rx-casino/client)","company":"rx-casino","website":null,"author":"rx-casino","vendor":"Sumsub","score":54,"first_seen":1784236521706,"last_seen":1784236521706},{"id":"gh_1275266339","name":"zentto-erp/zentto-web3-frontend","source":"GitHub","vertical":"identity","term":"KYC / identity","w":5,"ms":1782126164000,"eng":0,"url":"https://github.com/zentto-erp/zentto-web3-frontend","desc":"Frontend Next.js del neobanco cripto custodial Zentto Web3: backoffice de operación (KYC, disputas P2P, custodia, tesorería) + banca personal. Auth httpOnly+CSRF+2FA. Tauri escritorio/móvil.","author":"zentto-erp","company":"Zentto ERP","website":"https://zentto.net","score":52,"first_seen":1784236521706,"last_seen":1784236521706},{"id":"hn_48620588","name":"Anthropic uses Persona for identity verification","source":"Hacker News","company":"web","vertical":"identity","term":"KYC / identity","w":5,"ms":1782061786000,"eng":5,"url":"https://web.archive.org/web/20260415064244/https://support.claude.com/en/articles/14328960-identity-verification-on-claude","author":"Trung0246","score":52,"first_seen":1784236521706,"last_seen":1784236521706},{"id":"hire_blockchain","name":"Blockchain","source":"Hiring","company":"Blockchain","vertical":"identity","term":"hiring: Compliance Manager","w":4,"ms":1782332383000,"eng":60,"url":"https://job-boards.greenhouse.io/blockchain/jobs/8002957","desc":"Open roles: Compliance Manager · FinCrime (AML) Analyst","author":"Blockchain","score":51,"first_seen":1784236521706,"last_seen":1784236521706},{"id":"code_marlonucal","name":"marlonucal/marlon-client","source":"Building with","vertical":"identity","term":"uses Onfido","w":4,"ms":1782419567000,"eng":0,"url":"https://github.com/marlonucal/marlon-client","desc":"Ships the Onfido SDK in production code (marlonucal/marlon-client)","company":"marlonucal","website":null,"author":"marlonucal","vendor":"Onfido","score":48,"first_seen":1784236521706,"last_seen":1784236521706},{"id":"hn_48478504","name":"New Anthropic privacy policy: age/identity verification for consumer accounts","source":"Hacker News","company":"anthropic","vertical":"identity","term":"KYC / identity","w":5,"ms":1781107917000,"eng":12,"url":"https://www.anthropic.com/legal/privacy","author":"vhantz","score":46,"first_seen":1784236521706,"last_seen":1784236521706},{"id":"hn_48329025","name":"Unigox NeoBank-as-a-Service – ship a branded crypto neobank in 4 weeks","source":"Hacker News","company":"unigox","vertical":"fintech","term":"banking app","w":5,"ms":1780087636000,"eng":2,"url":"https://www.unigox.com/blog/what-we-learned-building-a-neobank-from-scratch","author":"skyzer","score":45,"first_seen":1784236521706,"last_seen":1784236521706},{"id":"code_nevy11","name":"Nevy11/Vault","source":"Building with","vertical":"identity","term":"uses Onfido","w":4,"ms":1782217185000,"eng":0,"url":"https://github.com/Nevy11/Vault","desc":"Ships the Onfido SDK in production code (Nevy11/Vault)","company":"Nevy11","website":"https://portfolio.vault-os.workers.dev/","author":"nevy11","vendor":"Onfido","score":45,"first_seen":1784236521706,"last_seen":1784236521706},{"id":"hire_luno","name":"Luno","source":"Hiring","company":"Luno","vertical":"identity","term":"hiring: AML Operations Analyst - Transaction Monitoring","w":4,"ms":1781853619000,"eng":60,"url":"https://job-boards.greenhouse.io/luno/jobs/7941789","desc":"Open roles: AML Operations Analyst - Transaction Monitoring · Compliance Auditor","author":"Luno","score":44,"first_seen":1784236521706,"last_seen":1784236521706},{"id":"gh_1273656200","name":"ruslanhaibatov/ux-ui-design-fridenli","source":"GitHub","vertical":"fintech","term":"neobank","w":4,"ms":1782038753000,"eng":0,"url":"https://github.com/ruslanhaibatov/ux-ui-design-fridenli","desc":"цифровой финансовой платформы, которая помогает людям управлять своими деньгами без лишней бюрократии.(это учебный дизайн и никак не будет относиться к реальному fridenli).","author":"ruslanhaibatov","company":"Ruslan Haibatov","website":"mizetsuu-dev.vercel.app","score":42,"first_seen":1784236521706,"last_seen":1784236521706},{"id":"gh_1265859577","name":"ruslanhaibatov/fridenli-api-node","source":"GitHub","vertical":"fintech","term":"neobank","w":4,"ms":1781158967000,"eng":0,"url":"https://github.com/ruslanhaibatov/fridenli-api-node","desc":"node.js + express + postgresql api for auth, wallets, and transfers. register/login with bcrypt + jwt, create wallets in any iso currency, deposit funds, transfer safely with postgres transactions & row-level locks, and view full paginated transfer history.","author":"ruslanhaibatov","company":"Ruslan Haibatov","website":"mizetsuu-dev.vercel.app","score":36,"first_seen":1784236521706,"last_seen":1784236521706},{"id":"hn_46883424","name":"AVATrade's Credibility – A Fintech Perspective on User-Protection Gaps","source":"Hacker News","company":null,"vertical":"fintech","term":"fintech / payments","w":4,"ms":1770196224000,"eng":1,"url":"https://news.ycombinator.com/item?id=46883424","author":"ReviewShield","score":36,"first_seen":1784236521706,"last_seen":1784236521706},{"id":"code_424363283","name":"424363283/crypto","source":"Building with","vertical":"identity","term":"uses Onfido","w":4,"ms":1751703630000,"eng":0,"url":"https://github.com/424363283/crypto","desc":"Ships the Onfido SDK in production code (424363283/crypto)","company":"EZ","website":null,"author":"424363283","vendor":"Onfido","score":36,"first_seen":1784236521706,"last_seen":1784236521706},{"id":"code_mtnblanco","name":"mtnblanco/ours-ethglobal","source":"Building with","vertical":"identity","term":"uses Onfido","w":4,"ms":1763898993000,"eng":0,"url":"https://github.com/mtnblanco/ours-ethglobal","desc":"Ships the Onfido SDK in production code (mtnblanco/ours-ethglobal)","company":"mtn","website":null,"author":"mtnblanco","vendor":"Onfido","score":36,"first_seen":1784236521706,"last_seen":1784236521706},{"id":"code_nhahub","name":"nhahub/NHA-138","source":"Building with","vertical":"identity","term":"uses Onfido","w":4,"ms":1765956329000,"eng":0,"url":"https://github.com/nhahub/NHA-138","desc":"Ships the Onfido SDK in production code (nhahub/NHA-138)","company":"NHA DEPI R1","website":"https://skillsdynamix.com/en/","author":"nhahub","vendor":"Onfido","score":36,"first_seen":1784236521706,"last_seen":1784236521706},{"id":"code_aasthaj28","name":"aasthaj28/expensify","source":"Building with","vertical":"identity","term":"uses Onfido","w":4,"ms":1738003395000,"eng":0,"url":"https://github.com/aasthaj28/expensify","desc":"Ships the Onfido SDK in production code (aasthaj28/expensify)","company":"Aastha Joshi","website":null,"author":"aasthaj28","vendor":"Onfido","score":36,"first_seen":1784236521706,"last_seen":1784236521706},{"id":"code_korede-dotcom","name":"korede-dotcom/rockeypayout","source":"Building with","vertical":"identity","term":"uses Sumsub","w":4,"ms":1751927601000,"eng":0,"url":"https://github.com/korede-dotcom/rockeypayout","desc":"Ships the Sumsub SDK in production code (korede-dotcom/rockeypayout)","company":"korede-dotcom","website":null,"author":"korede-dotcom","vendor":"Sumsub","score":36,"first_seen":1784236521706,"last_seen":1784236521706},{"id":"code_radamesramirez0","name":"RadamesRamirez0/satoshi_web","source":"Building with","vertical":"identity","term":"uses Sumsub","w":4,"ms":1751405858000,"eng":0,"url":"https://github.com/RadamesRamirez0/satoshi_web","desc":"Ships the Sumsub SDK in production code (RadamesRamirez0/satoshi_web)","company":"Radames Ramirez","website":null,"author":"radamesramirez0","vendor":"Sumsub","score":36,"first_seen":1784236521706,"last_seen":1784236521706},{"id":"code_mihle-matimba","name":"mihle-matimba/mint-pwa","source":"Building with","vertical":"identity","term":"uses Sumsub","w":4,"ms":1770322279000,"eng":0,"url":"https://github.com/mihle-matimba/mint-pwa","desc":"Ships the Sumsub SDK in production code (mihle-matimba/mint-pwa)","company":"mihle-matimba","website":null,"author":"mihle-matimba","vendor":"Sumsub","score":36,"first_seen":1784236521706,"last_seen":1784236521706},{"id":"code_carlos-vega-instipp","name":"carlos-vega-instipp/sumsub-websdk-app","source":"Building with","vertical":"identity","term":"uses Sumsub","w":4,"ms":1770418522000,"eng":0,"url":"https://github.com/carlos-vega-instipp/sumsub-websdk-app","desc":"Ships the Sumsub SDK in production code (carlos-vega-instipp/sumsub-websdk-app)","company":"Carlos Vega Oyola","website":null,"author":"carlos-vega-instipp","vendor":"Sumsub","score":36,"first_seen":1784236521706,"last_seen":1784236521706},{"id":"code_xylicblue","name":"xylicblue/integration","source":"Building with","vertical":"identity","term":"uses Sumsub","w":4,"ms":1762368399000,"eng":0,"url":"https://github.com/xylicblue/integration","desc":"Ships the Sumsub SDK in production code (xylicblue/integration)","company":"mahad bin aamir","website":null,"author":"xylicblue","vendor":"Sumsub","score":36,"first_seen":1784236521706,"last_seen":1784236521706},{"id":"code_dev2025-sys","name":"dev2025-sys/Mccoin_Platform_Demo","source":"Building with","vertical":"identity","term":"uses Sumsub","w":4,"ms":1753425772000,"eng":0,"url":"https://github.com/dev2025-sys/Mccoin_Platform_Demo","desc":"Ships the Sumsub SDK in production code (dev2025-sys/Mccoin_Platform_Demo)","company":"dev2025-sys","website":null,"author":"dev2025-sys","vendor":"Sumsub","score":36,"first_seen":1784236521706,"last_seen":1784236521706},{"id":"code_paimondev-rwa","name":"PaimonDev-RWA/frontend","source":"Building with","vertical":"identity","term":"uses Sumsub","w":4,"ms":1755145462000,"eng":0,"url":"https://github.com/PaimonDev-RWA/frontend","desc":"Ships the Sumsub SDK in production code (PaimonDev-RWA/frontend)","company":"paimondev-rwa","website":null,"author":"paimondev-rwa","vendor":"Sumsub","score":36,"first_seen":1784236521706,"last_seen":1784236521706},{"id":"code_hectorcorredor9","name":"HectorCorredor9/spend-wallet","source":"Building with","vertical":"identity","term":"uses Sumsub","w":4,"ms":1774969240000,"eng":0,"url":"https://github.com/HectorCorredor9/spend-wallet","desc":"Ships the Sumsub SDK in production code (HectorCorredor9/spend-wallet)","company":"hectorcorredor9","website":null,"author":"hectorcorredor9","vendor":"Sumsub","score":36,"first_seen":1784236521706,"last_seen":1784236521706},{"id":"code_franklin0000","name":"franklin0000/redflag-source","source":"Building with","vertical":"identity","term":"uses Sumsub","w":4,"ms":1776520557000,"eng":1,"url":"https://github.com/franklin0000/redflag-source","desc":"Ships the Sumsub SDK in production code (franklin0000/redflag-source)","company":"franklin0000","website":null,"author":"franklin0000","vendor":"Sumsub","score":36,"first_seen":1784236521706,"last_seen":1784236521706}]}